postgres/__init__.py
postgres/runtime.py
postgres/tool.py
opsmate_tool_postgres-0.1.0a0.dist-info/METADATA
opsmate_tool_postgres-0.1.0a0.dist-info/WHEEL
opsmate_tool_postgres-0.1.0a0.dist-info/entry_points.txt
opsmate_tool_postgres-0.1.0a0.dist-info/licenses/LICENSE
opsmate_tool_postgres-0.1.0a0.dist-info/RECORD
