Metadata-Version: 2.4
Name: opsmate-tool-postgres
Version: 0.1.0a0
Summary: PostgreSQL tool for opsmate
Author-email: Jingkai He <jingkai@hey.com>
License: MIT License
License-File: LICENSE
Requires-Python: <4.0,>=3.10
Requires-Dist: opsmate
Requires-Dist: psycopg2-binary
